<?xml version='1.0' encoding='utf-8'?>
<!DOCTYPE sect1 PUBLIC "-//OASIS//DTD DocBook XML V4.5//EN"
  "http://www.oasis-open.org/docbook/xml/4.5/docbookx.dtd" [
  <!ENTITY % general-entities SYSTEM "../general.ent">
  %general-entities;
]>

<sect1 id="ch-system-man-db" role="wrap">
  <?dbhtml filename="man-db.html"?>

  <sect1info condition="script">
    <productname>man-db</productname>
    <productnumber>&man-db-version;</productnumber>
    <address>&man-db-url;</address>
  </sect1info>

  <title>Man-DB-&man-db-version;</title>

  <indexterm zone="ch-system-man-db">
    <primary sortas="a-Man-DB">Man-DB</primary>
  </indexterm>

  <sect2 role="package">
    <title/>

    <para>Man-DB 软件包包含用于查找和查看 man 页面的程序。</para>

    <segmentedlist>
      <segtitle>&buildtime;</segtitle>
      <segtitle>&diskspace;</segtitle>

      <seglistitem>
        <seg>&man-db-ch6-sbu;</seg>
        <seg>&man-db-ch6-du;</seg>
      </seglistitem>
    </segmentedlist>

  </sect2>

  <sect2 role="installation">
    <title>安装 Man-DB</title>

    <para>准备编译 Man-DB：</para>

<screen><userinput remap="configure">./configure --prefix=/usr                        \
            --docdir=/usr/share/doc/man-db-&man-db-version; \
            --sysconfdir=/etc                    \
            --disable-setuid                     \
            --with-browser=/usr/bin/lynx         \
            --with-vgrind=/usr/bin/vgrind        \
            --with-grap=/usr/bin/grap</userinput></screen>

    <variablelist>
      <title>配置选项的含义：</title>

      <varlistentry>
        <term><parameter>--disable-setuid</parameter> 程序调用 setuid。</term>
        <listitem>
          <para>为用户 <command>man</command> 禁止 <systemitem class="username">man</systemitem>.</para>
        </listitem>
      </varlistentry>

      <varlistentry>
        <term><parameter>--with-...</parameter></term>
        <listitem>
          <para>这些参数用于设置一些默认程序。<command>lynx</command> 是一个基于文本的网络浏览器（查看 BLFS 获取安装指令），<command>vgrind</command> 将程序源码转换为 Groff 输入，<command>grap</command> 在 Groof 文档排版图中非常有用。查看手册页通常并不需要  <command>vgrind</command> 和 <command>grap</command> 程序。它们并不是 LFS 或 BLFS 的一部分，但是如果需要的话你自己应该能够在完成 LFS 之后安装它们。</para>
        </listitem>
      </varlistentry>

    </variablelist>

    <para>编译软件包：</para>

<screen><userinput remap="make">make</userinput></screen>

   <para>用以下命令测试结果：</para>

<screen><userinput remap="test">make check</userinput></screen>

    <para>安装软件包：</para>

<screen><userinput remap="install">make install</userinput></screen>

    <para>移除到不存在用户的引用：</para>

<screen><userinput remap="install">sed -i "s:man root:root root:g" /usr/lib/tmpfiles.d/man-db.conf</userinput></screen>

  </sect2>

  <sect2>
    <title>LFS 中的非英语手册页</title>

    <para>下面的表格显示了 Man-DB 假定手册页安装到 <filename class="directory">/usr/share/man/&lt;ll&gt;</filename> 会使用的字符编码。除此之外，Man-DB 能正确判断安装到该目录的手册页是否采用 UTF-8 编码。</para>

    <!-- Origin: man-db-2.5.9/lib/encodings.c -->
    <table>
<title>传统 8 位手册页预期字符编码</title>
      <?dbfo table-width="6in" ?>

      <tgroup cols="4">

        <colspec colnum="1" colwidth="1.5in"/>
        <colspec colnum="2" colwidth="1in"/>
        <colspec colnum="3" colwidth="2.5in"/>
        <colspec colnum="4" colwidth="1in"/>

        <thead>
          <row>
            <entry>语言 (缩写)</entry>
            <entry>编码</entry>
            <entry>语言 (缩写)</entry>
            <entry>编码</entry>
          </row>
        </thead>

        <tbody>
          <row>
            <entry>Danish (da)</entry>
            <entry>ISO-8859-1</entry>
            <entry>Croatian (hr)</entry>
            <entry>ISO-8859-2</entry>
          </row>
          <row>
            <entry>German (de)</entry>
            <entry>ISO-8859-1</entry>
            <entry>Hungarian (hu)</entry>
            <entry>ISO-8859-2</entry>
          </row>
          <row>
            <entry>English (en)</entry>
            <entry>ISO-8859-1</entry>
            <entry>Japanese (ja)</entry>
            <entry>EUC-JP</entry>
          </row>
          <row>
            <entry>Spanish (es)</entry>
            <entry>ISO-8859-1</entry>
            <entry>Korean (ko)</entry>
            <entry>EUC-KR</entry>
          </row>
          <row>
            <entry>Estonian (et)</entry>
            <entry>ISO-8859-1</entry>
            <entry>Lithuanian (lt)</entry>
            <entry>ISO-8859-13</entry>
          </row>
          <row>
            <entry>Finnish (fi)</entry>
            <entry>ISO-8859-1</entry>
            <entry>Latvian (lv)</entry>
            <entry>ISO-8859-13</entry>
          </row>
          <row>
            <entry>French (fr)</entry>
            <entry>ISO-8859-1</entry>
            <entry>Macedonian (mk)</entry>
            <entry>ISO-8859-5</entry>
          </row>
          <row>
            <entry>Irish (ga)</entry>
            <entry>ISO-8859-1</entry>
            <entry>Polish (pl)</entry>
            <entry>ISO-8859-2</entry>
          </row>
          <row>
            <entry>Galician (gl)</entry>
            <entry>ISO-8859-1</entry>
            <entry>Romanian (ro)</entry>
            <entry>ISO-8859-2</entry>
          </row>
          <row>
            <entry>Indonesian (id)</entry>
            <entry>ISO-8859-1</entry>
            <entry>Russian (ru)</entry>
            <entry>KOI8-R</entry>
          </row>
          <row>
            <entry>Icelandic (is)</entry>
            <entry>ISO-8859-1</entry>
            <entry>Slovak (sk)</entry>
            <entry>ISO-8859-2</entry>
          </row>
          <row>
            <entry>Italian (it)</entry>
            <entry>ISO-8859-1</entry>
            <entry>Slovenian (sl)</entry>
            <entry>ISO-8859-2</entry>
          </row>
          <row>
            <entry>Norwegian Bokmal (nb)</entry>
            <entry>ISO-8859-1</entry>
            <entry>Serbian Latin (sr@latin)</entry>
            <entry>ISO-8859-2</entry>
          </row>
          <row>
            <entry>Dutch (nl)</entry>
            <entry>ISO-8859-1</entry>
            <entry>Serbian (sr)</entry>
            <entry>ISO-8859-5</entry>
          </row>
          <row>
            <entry>Norwegian Nynorsk (nn)</entry>
            <entry>ISO-8859-1</entry>
            <entry>Turkish (tr)</entry>
            <entry>ISO-8859-9</entry>
          </row>
          <row>
            <entry>Norwegian (no)</entry>
            <entry>ISO-8859-1</entry>
            <entry>Ukrainian (uk)</entry>
            <entry>KOI8-U</entry>
          </row>
          <row>
            <entry>Portuguese (pt)</entry>
            <entry>ISO-8859-1</entry>
            <entry>Vietnamese (vi)</entry>
            <entry>TCVN5712-1</entry>
          </row>
          <row>
            <entry>Swedish (sv)</entry>
            <entry>ISO-8859-1</entry>
            <entry>Simplified Chinese (zh_CN)</entry>
            <entry>GBK</entry>
          </row>
          <row>
            <entry>Belarusian (be)</entry>
            <entry>CP1251</entry>
            <entry>Simplified Chinese, Singapore (zh_SG)</entry>
            <entry>GBK</entry>
          </row>
          <row>
            <entry>Bulgarian (bg)</entry>
            <entry>CP1251</entry>
            <entry>Traditional Chinese, Hong Kong (zh_HK)</entry>
            <entry>BIG5HKSCS</entry>
          </row>
          <row>
            <entry>Czech (cs)</entry>
            <entry>ISO-8859-2</entry>
            <entry>Traditional Chinese (zh_TW)</entry>
            <entry>BIG5</entry>
          </row>
          <row>
            <entry>Greek (el)</entry>
            <entry>ISO-8859-7</entry>
            <entry></entry>
            <entry></entry>
          </row>

        </tbody>

      </tgroup>

    </table>

    <note>
      <para>手册页不支持不在列表中的语言。</para>
    </note>

  </sect2>

  <sect2 id="contents-man-db" role="content">
    <title>Man-DB 软件包内容</title>

    <segmentedlist>
      <segtitle>安装的程序</segtitle>
      <segtitle>安装的库</segtitle>
      <segtitle>安装的目录</segtitle>

      <seglistitem>
        <seg>accessdb, apropos (链接到 whatis), catman, lexgrog, man, mandb,
        manpath, whatis, 和  zsoelim</seg>
        <seg>libman.so 和 libmandb.so</seg>
        <seg>/usr/lib/man-db, /usr/libexec/man-db,
        和 /usr/share/doc/man-db-&man-db-version;</seg>
      </seglistitem>
    </segmentedlist>

    <variablelist>
      <bridgehead renderas="sect3">简要介绍</bridgehead>
      <?dbfo list-presentation="list"?>
      <?dbhtml list-presentation="table"?>

      <varlistentry id="accessdb">
        <term><command>accessdb</command></term>
        <listitem>
          <para>以人类可读形式转储 <command>whatis</command> 数据库</para>
          <indexterm zone="ch-system-man-db accessdb">
            <primary sortas="b-accessdb">accessdb</primary>
          </indexterm>
        </listitem>
      </varlistentry>

      <varlistentry id="apropos">
        <term><command>apropos</command></term>
        <listitem>
          <para>查询 <command>whatis</command> 数据库并显示包含指定字符串的系统命令的简要介绍</para>
          <indexterm zone="ch-system-man-db apropos">
            <primary sortas="b-apropos">apropos</primary>
          </indexterm>
        </listitem>
      </varlistentry>

      <varlistentry id="catman">
        <term><command>catman</command></term>
        <listitem>
          <para>创建或更新预格式化手册页</para>
          <indexterm zone="ch-system-man-db catman">
            <primary sortas="b-catman">catman</primary>
          </indexterm>
        </listitem>
      </varlistentry>

      <varlistentry id="lexgrog">
        <term><command>lexgrog</command></term>
        <listitem>
          <para>显示指定手册页的一行概要信息</para>
          <indexterm zone="ch-system-man-db lexgrog">
            <primary sortas="b-lexgrog">lexgrog</primary>
          </indexterm>
        </listitem>
      </varlistentry>

      <varlistentry id="man">
        <term><command>man</command></term>
        <listitem>
          <para>格式化并显示要求的手册页</para>
          <indexterm zone="ch-system-man-db man">
            <primary sortas="b-man">man</primary>
          </indexterm>
        </listitem>
      </varlistentry>

      <varlistentry id="mandb">
        <term><command>mandb</command></term>
        <listitem>
          <para>创建或更新 <command>whatis</command> 数据库</para>
          <indexterm zone="ch-system-man-db mandb">
            <primary sortas="b-mandb">mandb</primary>
          </indexterm>
        </listitem>
      </varlistentry>

      <varlistentry id="manpath">
        <term><command>manpath</command></term>
        <listitem>
          <para>基于 man.conf 中的设置和用户环境显示 $MANPATH 或 (如果没有设置 $MANPATH) 合适的搜索路径的内容</para>
          <indexterm zone="ch-system-man-db manpath">
            <primary sortas="b-manpath">manpath</primary>
          </indexterm>
        </listitem>
      </varlistentry>

      <varlistentry id="whatis">
        <term><command>whatis</command></term>
        <listitem>
          <para>查询 <command>whatis</command> 数据库并显示包含以给定关键字为独立字的系统命令的简要介绍</para>
          <indexterm zone="ch-system-man-db whatis">
            <primary sortas="b-whatis">whatis</primary>
          </indexterm>
        </listitem>
      </varlistentry>

      <varlistentry id="zsoelim">
        <term><command>zsoelim</command></term>
        <listitem>
          <para>读取文件并用提到的 <emphasis>file</emphasis> 的内容替换 <emphasis>.so
          file</emphasis> 格式的行</para>
          <indexterm zone="ch-system-man-db zsoelim">
            <primary sortas="b-zsoelim">zsoelim</primary>
          </indexterm>
        </listitem>
      </varlistentry>

      <varlistentry id="libman">
        <term><filename class="libraryfile">libman</filename></term>
        <listitem>
          <para>包含 <command>man</command> 的运行时支持</para>
          <indexterm zone="ch-system-man-db libman">
            <primary sortas="c-libman">libman</primary>
          </indexterm>
        </listitem>
      </varlistentry>

      <varlistentry id="libmandb">
        <term><filename class="libraryfile">libmandb</filename></term>
        <listitem>
          <para>包含 <command>man</command> 的运行时支持</para>
          <indexterm zone="ch-system-man-db libmandb">
            <primary sortas="c-libmandb">libmandb</primary>
          </indexterm>
        </listitem>
      </varlistentry>

    </variablelist>

  </sect2>

</sect1>
